smartbytes/__init__.py
smartbytes/smartbytes.py
smartbytes_monitor-0.1.6.dist-info/DESCRIPTION.rst
smartbytes_monitor-0.1.6.dist-info/METADATA
smartbytes_monitor-0.1.6.dist-info/RECORD
smartbytes_monitor-0.1.6.dist-info/WHEEL
smartbytes_monitor-0.1.6.dist-info/entry_points.txt
smartbytes_monitor-0.1.6.dist-info/metadata.json
smartbytes_monitor-0.1.6.dist-info/top_level.txt
