Metadata-Version: 2.0
Name: smartbytes-monitor
Version: 0.1.6
Summary: A Python package to monitor your Airtel Broadband network stats, remaining data, days left, etc
Home-page: https://www.github.com/ritiek/smartbytes-monitor
Author: Ritiek Malhotra
Author-email: ritiekmalhotra123@gmail.com
License: MIT
Download-URL: https://github.com/ritiek/smartbytes-monitor/archive/v0.1.6.tar.gz
Keywords: airtel,stats,monitor,data-usage,smartbytes-tracker
Platform: UNKNOWN
Requires-Dist: BeautifulSoup4
